polymorphic_fk/__init__.py
polymorphic_fk/fields.py
polymorphic_fk/static/admin/polymorphic_fk/polymorphic_fk.css
polymorphic_fk/static/admin/polymorphic_fk/polymorphic_fk.js
polymorphic_fk/tests/__init__.py
polymorphic_fk/tests/base.py
polymorphic_fk/tests/settings.py
polymorphic_fk/tests/urls.py
polymorphic_fk/tests/test_admin/__init__.py
polymorphic_fk/tests/test_admin/admin.py
polymorphic_fk/tests/test_admin/models.py
polymorphic_fk/tests/test_admin/test.py
polymorphic_fk/tests/test_admin/migrations/0001_initial.py
polymorphic_fk/tests/test_admin/migrations/__init__.py
django_polymorphic_foreignkey-2.0.0.dist-info/LICENSE
django_polymorphic_foreignkey-2.0.0.dist-info/METADATA
django_polymorphic_foreignkey-2.0.0.dist-info/WHEEL
django_polymorphic_foreignkey-2.0.0.dist-info/top_level.txt
django_polymorphic_foreignkey-2.0.0.dist-info/RECORD
